lamdenpy/__init__.py
lamdenpy/pow.py
lamdenpy/query.py
lamdenpy/tx.py
lamdenpy/wallet.py
lamdenpy-0.1.2.dist-info/METADATA
lamdenpy-0.1.2.dist-info/WHEEL
lamdenpy-0.1.2.dist-info/top_level.txt
lamdenpy-0.1.2.dist-info/RECORD
