Metadata-Version: 2.1
Name: lamdenpy
Version: 0.1.2
Summary: Python driver for the Lamden blockchain. Everything you need to integrate smart contracts with standard applications.
Home-page: https://github.com/Lamden/lampy
Author: Lamden
Author-email: team@lamden.io
License: Creative Commons Non-Commercial
Platform: UNKNOWN
Requires-Dist: requests
Requires-Dist: PyNaCl
